flopyrw/__init__.py
flopyrw/version.py
flopyrw/modpathrw/__init__.py
flopyrw/modpathrw/mprw.py
flopyrw/modpathrw/mprwbas.py
flopyrw/modpathrw/mprwdsp.py
flopyrw/modpathrw/mprwgpkde.py
flopyrw/modpathrw/mprwic.py
flopyrw/modpathrw/mprwimp.py
flopyrw/modpathrw/mprwobs.py
flopyrw/modpathrw/mprwopts.py
flopyrw/modpathrw/mprwparticlegroup.py
flopyrw/modpathrw/mprwsim.py
flopyrw/modpathrw/mprwspc.py
flopyrw/modpathrw/mprwsrc.py
flopyrw/modpathrw/utils.py
flopyrw-1.0.3.dist-info/licenses/LICENSE.md
flopyrw-1.0.3.dist-info/METADATA
flopyrw-1.0.3.dist-info/WHEEL
flopyrw-1.0.3.dist-info/top_level.txt
flopyrw-1.0.3.dist-info/RECORD
