Metadata-Version: 2.4
Name: flopyrw
Version: 1.0.3
Summary: Python interface based on FloPy to configure input files for MODPATH-RW
Keywords: MODPATH-RW,hydrogeology,rwpt
Requires-Python: >=3.8
License-File: LICENSE.md
Requires-Dist: flopy>=3.5
Provides-Extra: test
Requires-Dist: shapely>=1.8; extra == "test"
Requires-Dist: pyshp; extra == "test"
Requires-Dist: modflow-devtools; extra == "test"
Requires-Dist: pytest; extra == "test"
Dynamic: license-file
